python/upd_cli/__init__.py
python/upd_cli/__main__.py
python/upd_cli/py.typed
upd_cli-0.0.20.data/scripts/upd.exe
upd_cli-0.0.20.dist-info/METADATA
upd_cli-0.0.20.dist-info/WHEEL
upd_cli-0.0.20.dist-info/licenses/LICENSE
upd_cli-0.0.20.dist-info/RECORD
