Metadata-Version: 2.4
Name: upd-cli
Version: 0.0.20
Classifier: Development Status :: 4 - Beta
Classifier: Environment :: Console
Classifier: Intended Audience :: Developers
Classifier: License :: OSI Approved :: MIT License
Classifier: Operating System :: OS Independent
Classifier: Programming Language :: Python :: 3
Classifier: Programming Language :: Rust
Classifier: Topic :: Software Development :: Build Tools
License-File: LICENSE
Summary: A fast dependency updater for Python and Node.js projects
Keywords: dependencies,update,python,nodejs,npm
Home-Page: https://github.com/rvben/upd
Author-email: Ruben Jongejan <ruben.jongejan@gmail.com>
License: MIT
Requires-Python: >=3.8
Project-URL: Homepage, https://github.com/rvben/upd
Project-URL: Repository, https://github.com/rvben/upd
Project-URL: Documentation, https://github.com/rvben/upd#readme
